{
  "Protocol": {
    "Magic": 100518,
    "AddressVersion": 1,
    "SecondsPerBlock": 20,
    "StandbyValidators": [
      "",
      "",
      "",
      "",
      "",
      "",
      ""
    ],
    "SeedList": [
      "seed1.trustedu.network:10058",
      "seed2.trustedu.network:10058",
      "seed3.trustedu.network:10058",
      "seed4.trustedu.network:10058",
      "seed5.trustedu.network:10058"
    ],
    "SystemFee": {
      "EnrollmentTransaction": 500,
      "IssueTransaction": 250,
      "PublishTransaction": 250,
      "RegisterTransaction": 5000
    }
  }
}